{
  "version": "7",
  "dialect": "postgresql",
  "entries": [
    {
      "idx": 0,
      "version": "7",
      "when": 1740255513834,
      "tag": "0000_oval_gravity",
      "breakpoints": true
    },
    {
      "idx": 1,
      "version": "7",
      "when": 1740257791837,
      "tag": "0001_skinny_tombstone",
      "breakpoints": true
    },
    {
      "idx": 2,
      "version": "7",
      "when": 1740257905221,
      "tag": "0002_green_moon_knight",
      "breakpoints": true
    },
    {
      "idx": 3,
      "version": "7",
      "when": 1740258242367,
      "tag": "0003_special_loners",
      "breakpoints": true
    },
    {
      "idx": 4,
      "version": "7",
      "when": 1740258650529,
      "tag": "0004_odd_james_howlett",
      "breakpoints": true
    }
  ]
}